{"nodes": [{"id": "c_users_vatsal_document_vscodefiles_pythoncode_smartdashboardmaker_backend_routers_dashboards_py", "label": "dashboards.py", "file_type": "code", "source_file": "C:\\Users\\Vatsal\\Document\\VSCodeFiles\\PythonCode\\SmartDashBoardMaker\\backend\\routers\\dashboards.py", "source_location": "L1"}, {"id": "dashboards_dashboardbase", "label": "DashboardBase", "file_type": "code", "source_file": "C:\\Users\\Vatsal\\Document\\VSCodeFiles\\PythonCode\\SmartDashBoardMaker\\backend\\routers\\dashboards.py", "source_location": "L10"}, {"id": "basemodel", "label": "BaseModel", "file_type": "code", "source_file": "", "source_location": ""}, {"id": "dashboards_dashboardupdate", "label": "DashboardUpdate", "file_type": "code", "source_file": "C:\\Users\\Vatsal\\Document\\VSCodeFiles\\PythonCode\\SmartDashBoardMaker\\backend\\routers\\dashboards.py", "source_location": "L18"}, {"id": "dashboards_list_dashboards", "label": "list_dashboards()", "file_type": "code", "source_file": "C:\\Users\\Vatsal\\Document\\VSCodeFiles\\PythonCode\\SmartDashBoardMaker\\backend\\routers\\dashboards.py", "source_location": "L27"}, {"id": "dashboards_get_dashboard", "label": "get_dashboard()", "file_type": "code", "source_file": "C:\\Users\\Vatsal\\Document\\VSCodeFiles\\PythonCode\\SmartDashBoardMaker\\backend\\routers\\dashboards.py", "source_location": "L45"}, {"id": "dashboards_save_dashboard", "label": "save_dashboard()", "file_type": "code", "source_file": "C:\\Users\\Vatsal\\Document\\VSCodeFiles\\PythonCode\\SmartDashBoardMaker\\backend\\routers\\dashboards.py", "source_location": "L64"}, {"id": "dashboards_update_dashboard", "label": "update_dashboard()", "file_type": "code", "source_file": "C:\\Users\\Vatsal\\Document\\VSCodeFiles\\PythonCode\\SmartDashBoardMaker\\backend\\routers\\dashboards.py", "source_location": "L89"}, {"id": "dashboards_delete_dashboard", "label": "delete_dashboard()", "file_type": "code", "source_file": "C:\\Users\\Vatsal\\Document\\VSCodeFiles\\PythonCode\\SmartDashBoardMaker\\backend\\routers\\dashboards.py", "source_location": "L122"}], "edges": [{"source": "c_users_vatsal_document_vscodefiles_pythoncode_smartdashboardmaker_backend_routers_dashboards_py", "target": "json", "relation": "imports", "confidence": "EXTRACTED", "source_file": "C:\\Users\\Vatsal\\Document\\VSCodeFiles\\PythonCode\\SmartDashBoardMaker\\backend\\routers\\dashboards.py", "source_location": "L1", "weight": 1.0}, {"source": "c_users_vatsal_document_vscodefiles_pythoncode_smartdashboardmaker_backend_routers_dashboards_py", "target": "fastapi", "relation": "imports_from", "confidence": "EXTRACTED", "source_file": "C:\\Users\\Vatsal\\Document\\VSCodeFiles\\PythonCode\\SmartDashBoardMaker\\backend\\routers\\dashboards.py", "source_location": "L2", "weight": 1.0}, {"source": "c_users_vatsal_document_vscodefiles_pythoncode_smartdashboardmaker_backend_routers_dashboards_py", "target": "typing", "relation": "imports_from", "confidence": "EXTRACTED", "source_file": "C:\\Users\\Vatsal\\Document\\VSCodeFiles\\PythonCode\\SmartDashBoardMaker\\backend\\routers\\dashboards.py", "source_location": "L3", "weight": 1.0}, {"source": "c_users_vatsal_document_vscodefiles_pythoncode_smartdashboardmaker_backend_routers_dashboards_py", "target": "pydantic", "relation": "imports_from", "confidence": "EXTRACTED", "source_file": "C:\\Users\\Vatsal\\Document\\VSCodeFiles\\PythonCode\\SmartDashBoardMaker\\backend\\routers\\dashboards.py", "source_location": "L4", "weight": 1.0}, {"source": "c_users_vatsal_document_vscodefiles_pythoncode_smartdashboardmaker_backend_routers_dashboards_py", "target": "models_database", "relation": "imports_from", "confidence": "EXTRACTED", "source_file": "C:\\Users\\Vatsal\\Document\\VSCodeFiles\\PythonCode\\SmartDashBoardMaker\\backend\\routers\\dashboards.py", "source_location": "L5", "weight": 1.0}, {"source": "c_users_vatsal_document_vscodefiles_pythoncode_smartdashboardmaker_backend_routers_dashboards_py", "target": "uuid", "relation": "imports", "confidence": "EXTRACTED", "source_file": "C:\\Users\\Vatsal\\Document\\VSCodeFiles\\PythonCode\\SmartDashBoardMaker\\backend\\routers\\dashboards.py", "source_location": "L6", "weight": 1.0}, {"source": "c_users_vatsal_document_vscodefiles_pythoncode_smartdashboardmaker_backend_routers_dashboards_py", "target": "dashboards_dashboardbase", "relation": "contains", "confidence": "EXTRACTED", "source_file": "C:\\Users\\Vatsal\\Document\\VSCodeFiles\\PythonCode\\SmartDashBoardMaker\\backend\\routers\\dashboards.py", "source_location": "L10", "weight": 1.0}, {"source": "dashboards_dashboardbase", "target": "basemodel", "relation": "inherits", "confidence": "EXTRACTED", "source_file": "C:\\Users\\Vatsal\\Document\\VSCodeFiles\\PythonCode\\SmartDashBoardMaker\\backend\\routers\\dashboards.py", "source_location": "L10", "weight": 1.0}, {"source": "c_users_vatsal_document_vscodefiles_pythoncode_smartdashboardmaker_backend_routers_dashboards_py", "target": "dashboards_dashboardupdate", "relation": "contains", "confidence": "EXTRACTED", "source_file": "C:\\Users\\Vatsal\\Document\\VSCodeFiles\\PythonCode\\SmartDashBoardMaker\\backend\\routers\\dashboards.py", "source_location": "L18", "weight": 1.0}, {"source": "dashboards_dashboardupdate", "target": "basemodel", "relation": "inherits", "confidence": "EXTRACTED", "source_file": "C:\\Users\\Vatsal\\Document\\VSCodeFiles\\PythonCode\\SmartDashBoardMaker\\backend\\routers\\dashboards.py", "source_location": "L18", "weight": 1.0}, {"source": "c_users_vatsal_document_vscodefiles_pythoncode_smartdashboardmaker_backend_routers_dashboards_py", "target": "dashboards_list_dashboards", "relation": "contains", "confidence": "EXTRACTED", "source_file": "C:\\Users\\Vatsal\\Document\\VSCodeFiles\\PythonCode\\SmartDashBoardMaker\\backend\\routers\\dashboards.py", "source_location": "L27", "weight": 1.0}, {"source": "c_users_vatsal_document_vscodefiles_pythoncode_smartdashboardmaker_backend_routers_dashboards_py", "target": "dashboards_get_dashboard", "relation": "contains", "confidence": "EXTRACTED", "source_file": "C:\\Users\\Vatsal\\Document\\VSCodeFiles\\PythonCode\\SmartDashBoardMaker\\backend\\routers\\dashboards.py", "source_location": "L45", "weight": 1.0}, {"source": "c_users_vatsal_document_vscodefiles_pythoncode_smartdashboardmaker_backend_routers_dashboards_py", "target": "dashboards_save_dashboard", "relation": "contains", "confidence": "EXTRACTED", "source_file": "C:\\Users\\Vatsal\\Document\\VSCodeFiles\\PythonCode\\SmartDashBoardMaker\\backend\\routers\\dashboards.py", "source_location": "L64", "weight": 1.0}, {"source": "c_users_vatsal_document_vscodefiles_pythoncode_smartdashboardmaker_backend_routers_dashboards_py", "target": "dashboards_update_dashboard", "relation": "contains", "confidence": "EXTRACTED", "source_file": "C:\\Users\\Vatsal\\Document\\VSCodeFiles\\PythonCode\\SmartDashBoardMaker\\backend\\routers\\dashboards.py", "source_location": "L89", "weight": 1.0}, {"source": "c_users_vatsal_document_vscodefiles_pythoncode_smartdashboardmaker_backend_routers_dashboards_py", "target": "dashboards_delete_dashboard", "relation": "contains", "confidence": "EXTRACTED", "source_file": "C:\\Users\\Vatsal\\Document\\VSCodeFiles\\PythonCode\\SmartDashBoardMaker\\backend\\routers\\dashboards.py", "source_location": "L122", "weight": 1.0}], "raw_calls": [{"caller_nid": "dashboards_list_dashboards", "callee": "get_db", "source_file": "C:\\Users\\Vatsal\\Document\\VSCodeFiles\\PythonCode\\SmartDashBoardMaker\\backend\\routers\\dashboards.py", "source_location": "L28"}, {"caller_nid": "dashboards_list_dashboards", "callee": "execute", "source_file": "C:\\Users\\Vatsal\\Document\\VSCodeFiles\\PythonCode\\SmartDashBoardMaker\\backend\\routers\\dashboards.py", "source_location": "L29"}, {"caller_nid": "dashboards_list_dashboards", "callee": "fetchall", "source_file": "C:\\Users\\Vatsal\\Document\\VSCodeFiles\\PythonCode\\SmartDashBoardMaker\\backend\\routers\\dashboards.py", "source_location": "L31"}, {"caller_nid": "dashboards_list_dashboards", "callee": "dict", "source_file": "C:\\Users\\Vatsal\\Document\\VSCodeFiles\\PythonCode\\SmartDashBoardMaker\\backend\\routers\\dashboards.py", "source_location": "L32"}, {"caller_nid": "dashboards_list_dashboards", "callee": "loads", "source_file": "C:\\Users\\Vatsal\\Document\\VSCodeFiles\\PythonCode\\SmartDashBoardMaker\\backend\\routers\\dashboards.py", "source_location": "L33"}, {"caller_nid": "dashboards_list_dashboards", "callee": "get", "source_file": "C:\\Users\\Vatsal\\Document\\VSCodeFiles\\PythonCode\\SmartDashBoardMaker\\backend\\routers\\dashboards.py", "source_location": "L33"}, {"caller_nid": "dashboards_list_dashboards", "callee": "loads", "source_file": "C:\\Users\\Vatsal\\Document\\VSCodeFiles\\PythonCode\\SmartDashBoardMaker\\backend\\routers\\dashboards.py", "source_location": "L35"}, {"caller_nid": "dashboards_list_dashboards", "callee": "get", "source_file": "C:\\Users\\Vatsal\\Document\\VSCodeFiles\\PythonCode\\SmartDashBoardMaker\\backend\\routers\\dashboards.py", "source_location": "L35"}, {"caller_nid": "dashboards_list_dashboards", "callee": "loads", "source_file": "C:\\Users\\Vatsal\\Document\\VSCodeFiles\\PythonCode\\SmartDashBoardMaker\\backend\\routers\\dashboards.py", "source_location": "L37"}, {"caller_nid": "dashboards_list_dashboards", "callee": "get", "source_file": "C:\\Users\\Vatsal\\Document\\VSCodeFiles\\PythonCode\\SmartDashBoardMaker\\backend\\routers\\dashboards.py", "source_location": "L37"}, {"caller_nid": "dashboards_list_dashboards", "callee": "loads", "source_file": "C:\\Users\\Vatsal\\Document\\VSCodeFiles\\PythonCode\\SmartDashBoardMaker\\backend\\routers\\dashboards.py", "source_location": "L39"}, {"caller_nid": "dashboards_list_dashboards", "callee": "get", "source_file": "C:\\Users\\Vatsal\\Document\\VSCodeFiles\\PythonCode\\SmartDashBoardMaker\\backend\\routers\\dashboards.py", "source_location": "L39"}, {"caller_nid": "dashboards_list_dashboards", "callee": "append", "source_file": "C:\\Users\\Vatsal\\Document\\VSCodeFiles\\PythonCode\\SmartDashBoardMaker\\backend\\routers\\dashboards.py", "source_location": "L41"}, {"caller_nid": "dashboards_get_dashboard", "callee": "get_db", "source_file": "C:\\Users\\Vatsal\\Document\\VSCodeFiles\\PythonCode\\SmartDashBoardMaker\\backend\\routers\\dashboards.py", "source_location": "L46"}, {"caller_nid": "dashboards_get_dashboard", "callee": "execute", "source_file": "C:\\Users\\Vatsal\\Document\\VSCodeFiles\\PythonCode\\SmartDashBoardMaker\\backend\\routers\\dashboards.py", "source_location": "L47"}, {"caller_nid": "dashboards_get_dashboard", "callee": "fetchone", "source_file": "C:\\Users\\Vatsal\\Document\\VSCodeFiles\\PythonCode\\SmartDashBoardMaker\\backend\\routers\\dashboards.py", "source_location": "L48"}, {"caller_nid": "dashboards_get_dashboard", "callee": "HTTPException", "source_file": "C:\\Users\\Vatsal\\Document\\VSCodeFiles\\PythonCode\\SmartDashBoardMaker\\backend\\routers\\dashboards.py", "source_location": "L50"}, {"caller_nid": "dashboards_get_dashboard", "callee": "dict", "source_file": "C:\\Users\\Vatsal\\Document\\VSCodeFiles\\PythonCode\\SmartDashBoardMaker\\backend\\routers\\dashboards.py", "source_location": "L52"}, {"caller_nid": "dashboards_get_dashboard", "callee": "loads", "source_file": "C:\\Users\\Vatsal\\Document\\VSCodeFiles\\PythonCode\\SmartDashBoardMaker\\backend\\routers\\dashboards.py", "source_location": "L53"}, {"caller_nid": "dashboards_get_dashboard", "callee": "get", "source_file": "C:\\Users\\Vatsal\\Document\\VSCodeFiles\\PythonCode\\SmartDashBoardMaker\\backend\\routers\\dashboards.py", "source_location": "L53"}, {"caller_nid": "dashboards_get_dashboard", "callee": "loads", "source_file": "C:\\Users\\Vatsal\\Document\\VSCodeFiles\\PythonCode\\SmartDashBoardMaker\\backend\\routers\\dashboards.py", "source_location": "L55"}, {"caller_nid": "dashboards_get_dashboard", "callee": "get", "source_file": "C:\\Users\\Vatsal\\Document\\VSCodeFiles\\PythonCode\\SmartDashBoardMaker\\backend\\routers\\dashboards.py", "source_location": "L55"}, {"caller_nid": "dashboards_get_dashboard", "callee": "loads", "source_file": "C:\\Users\\Vatsal\\Document\\VSCodeFiles\\PythonCode\\SmartDashBoardMaker\\backend\\routers\\dashboards.py", "source_location": "L57"}, {"caller_nid": "dashboards_get_dashboard", "callee": "get", "source_file": "C:\\Users\\Vatsal\\Document\\VSCodeFiles\\PythonCode\\SmartDashBoardMaker\\backend\\routers\\dashboards.py", "source_location": "L57"}, {"caller_nid": "dashboards_get_dashboard", "callee": "loads", "source_file": "C:\\Users\\Vatsal\\Document\\VSCodeFiles\\PythonCode\\SmartDashBoardMaker\\backend\\routers\\dashboards.py", "source_location": "L59"}, {"caller_nid": "dashboards_get_dashboard", "callee": "get", "source_file": "C:\\Users\\Vatsal\\Document\\VSCodeFiles\\PythonCode\\SmartDashBoardMaker\\backend\\routers\\dashboards.py", "source_location": "L59"}, {"caller_nid": "dashboards_save_dashboard", "callee": "str", "source_file": "C:\\Users\\Vatsal\\Document\\VSCodeFiles\\PythonCode\\SmartDashBoardMaker\\backend\\routers\\dashboards.py", "source_location": "L65"}, {"caller_nid": "dashboards_save_dashboard", "callee": "uuid4", "source_file": "C:\\Users\\Vatsal\\Document\\VSCodeFiles\\PythonCode\\SmartDashBoardMaker\\backend\\routers\\dashboards.py", "source_location": "L65"}, {"caller_nid": "dashboards_save_dashboard", "callee": "get_db", "source_file": "C:\\Users\\Vatsal\\Document\\VSCodeFiles\\PythonCode\\SmartDashBoardMaker\\backend\\routers\\dashboards.py", "source_location": "L66"}, {"caller_nid": "dashboards_save_dashboard", "callee": "execute", "source_file": "C:\\Users\\Vatsal\\Document\\VSCodeFiles\\PythonCode\\SmartDashBoardMaker\\backend\\routers\\dashboards.py", "source_location": "L67"}, {"caller_nid": "dashboards_save_dashboard", "callee": "dumps", "source_file": "C:\\Users\\Vatsal\\Document\\VSCodeFiles\\PythonCode\\SmartDashBoardMaker\\backend\\routers\\dashboards.py", "source_location": "L74"}, {"caller_nid": "dashboards_save_dashboard", "callee": "dumps", "source_file": "C:\\Users\\Vatsal\\Document\\VSCodeFiles\\PythonCode\\SmartDashBoardMaker\\backend\\routers\\dashboards.py", "source_location": "L75"}, {"caller_nid": "dashboards_save_dashboard", "callee": "dumps", "source_file": "C:\\Users\\Vatsal\\Document\\VSCodeFiles\\PythonCode\\SmartDashBoardMaker\\backend\\routers\\dashboards.py", "source_location": "L76"}, {"caller_nid": "dashboards_save_dashboard", "callee": "dumps", "source_file": "C:\\Users\\Vatsal\\Document\\VSCodeFiles\\PythonCode\\SmartDashBoardMaker\\backend\\routers\\dashboards.py", "source_location": "L77"}, {"caller_nid": "dashboards_save_dashboard", "callee": "execute", "source_file": "C:\\Users\\Vatsal\\Document\\VSCodeFiles\\PythonCode\\SmartDashBoardMaker\\backend\\routers\\dashboards.py", "source_location": "L79"}, {"caller_nid": "dashboards_save_dashboard", "callee": "fetchone", "source_file": "C:\\Users\\Vatsal\\Document\\VSCodeFiles\\PythonCode\\SmartDashBoardMaker\\backend\\routers\\dashboards.py", "source_location": "L80"}, {"caller_nid": "dashboards_save_dashboard", "callee": "dict", "source_file": "C:\\Users\\Vatsal\\Document\\VSCodeFiles\\PythonCode\\SmartDashBoardMaker\\backend\\routers\\dashboards.py", "source_location": "L81"}, {"caller_nid": "dashboards_save_dashboard", "callee": "loads", "source_file": "C:\\Users\\Vatsal\\Document\\VSCodeFiles\\PythonCode\\SmartDashBoardMaker\\backend\\routers\\dashboards.py", "source_location": "L82"}, {"caller_nid": "dashboards_save_dashboard", "callee": "loads", "source_file": "C:\\Users\\Vatsal\\Document\\VSCodeFiles\\PythonCode\\SmartDashBoardMaker\\backend\\routers\\dashboards.py", "source_location": "L83"}, {"caller_nid": "dashboards_save_dashboard", "callee": "loads", "source_file": "C:\\Users\\Vatsal\\Document\\VSCodeFiles\\PythonCode\\SmartDashBoardMaker\\backend\\routers\\dashboards.py", "source_location": "L84"}, {"caller_nid": "dashboards_save_dashboard", "callee": "loads", "source_file": "C:\\Users\\Vatsal\\Document\\VSCodeFiles\\PythonCode\\SmartDashBoardMaker\\backend\\routers\\dashboards.py", "source_location": "L85"}, {"caller_nid": "dashboards_update_dashboard", "callee": "get_db", "source_file": "C:\\Users\\Vatsal\\Document\\VSCodeFiles\\PythonCode\\SmartDashBoardMaker\\backend\\routers\\dashboards.py", "source_location": "L90"}, {"caller_nid": "dashboards_update_dashboard", "callee": "execute", "source_file": "C:\\Users\\Vatsal\\Document\\VSCodeFiles\\PythonCode\\SmartDashBoardMaker\\backend\\routers\\dashboards.py", "source_location": "L91"}, {"caller_nid": "dashboards_update_dashboard", "callee": "fetchone", "source_file": "C:\\Users\\Vatsal\\Document\\VSCodeFiles\\PythonCode\\SmartDashBoardMaker\\backend\\routers\\dashboards.py", "source_location": "L92"}, {"caller_nid": "dashboards_update_dashboard", "callee": "HTTPException", "source_file": "C:\\Users\\Vatsal\\Document\\VSCodeFiles\\PythonCode\\SmartDashBoardMaker\\backend\\routers\\dashboards.py", "source_location": "L94"}, {"caller_nid": "dashboards_update_dashboard", "callee": "dict", "source_file": "C:\\Users\\Vatsal\\Document\\VSCodeFiles\\PythonCode\\SmartDashBoardMaker\\backend\\routers\\dashboards.py", "source_location": "L96"}, {"caller_nid": "dashboards_update_dashboard", "callee": "dumps", "source_file": "C:\\Users\\Vatsal\\Document\\VSCodeFiles\\PythonCode\\SmartDashBoardMaker\\backend\\routers\\dashboards.py", "source_location": "L101"}, {"caller_nid": "dashboards_update_dashboard", "callee": "dumps", "source_file": "C:\\Users\\Vatsal\\Document\\VSCodeFiles\\PythonCode\\SmartDashBoardMaker\\backend\\routers\\dashboards.py", "source_location": "L102"}, {"caller_nid": "dashboards_update_dashboard", "callee": "dumps", "source_file": "C:\\Users\\Vatsal\\Document\\VSCodeFiles\\PythonCode\\SmartDashBoardMaker\\backend\\routers\\dashboards.py", "source_location": "L103"}, {"caller_nid": "dashboards_update_dashboard", "callee": "dumps", "source_file": "C:\\Users\\Vatsal\\Document\\VSCodeFiles\\PythonCode\\SmartDashBoardMaker\\backend\\routers\\dashboards.py", "source_location": "L104"}, {"caller_nid": "dashboards_update_dashboard", "callee": "execute", "source_file": "C:\\Users\\Vatsal\\Document\\VSCodeFiles\\PythonCode\\SmartDashBoardMaker\\backend\\routers\\dashboards.py", "source_location": "L106"}, {"caller_nid": "dashboards_update_dashboard", "callee": "execute", "source_file": "C:\\Users\\Vatsal\\Document\\VSCodeFiles\\PythonCode\\SmartDashBoardMaker\\backend\\routers\\dashboards.py", "source_location": "L112"}, {"caller_nid": "dashboards_update_dashboard", "callee": "fetchone", "source_file": "C:\\Users\\Vatsal\\Document\\VSCodeFiles\\PythonCode\\SmartDashBoardMaker\\backend\\routers\\dashboards.py", "source_location": "L113"}, {"caller_nid": "dashboards_update_dashboard", "callee": "dict", "source_file": "C:\\Users\\Vatsal\\Document\\VSCodeFiles\\PythonCode\\SmartDashBoardMaker\\backend\\routers\\dashboards.py", "source_location": "L114"}, {"caller_nid": "dashboards_update_dashboard", "callee": "loads", "source_file": "C:\\Users\\Vatsal\\Document\\VSCodeFiles\\PythonCode\\SmartDashBoardMaker\\backend\\routers\\dashboards.py", "source_location": "L115"}, {"caller_nid": "dashboards_update_dashboard", "callee": "loads", "source_file": "C:\\Users\\Vatsal\\Document\\VSCodeFiles\\PythonCode\\SmartDashBoardMaker\\backend\\routers\\dashboards.py", "source_location": "L116"}, {"caller_nid": "dashboards_update_dashboard", "callee": "loads", "source_file": "C:\\Users\\Vatsal\\Document\\VSCodeFiles\\PythonCode\\SmartDashBoardMaker\\backend\\routers\\dashboards.py", "source_location": "L117"}, {"caller_nid": "dashboards_update_dashboard", "callee": "loads", "source_file": "C:\\Users\\Vatsal\\Document\\VSCodeFiles\\PythonCode\\SmartDashBoardMaker\\backend\\routers\\dashboards.py", "source_location": "L118"}, {"caller_nid": "dashboards_delete_dashboard", "callee": "get_db", "source_file": "C:\\Users\\Vatsal\\Document\\VSCodeFiles\\PythonCode\\SmartDashBoardMaker\\backend\\routers\\dashboards.py", "source_location": "L123"}, {"caller_nid": "dashboards_delete_dashboard", "callee": "execute", "source_file": "C:\\Users\\Vatsal\\Document\\VSCodeFiles\\PythonCode\\SmartDashBoardMaker\\backend\\routers\\dashboards.py", "source_location": "L124"}]}