{"nodes": [{"id": "c_users_vatsal_document_vscodefiles_pythoncode_smartdashboardmaker_frontend_src_lib_querybuilderutils_jsx", "label": "queryBuilderUtils.jsx", "file_type": "code", "source_file": "C:\\Users\\Vatsal\\Document\\VSCodeFiles\\PythonCode\\SmartDashBoardMaker\\frontend\\src\\lib\\queryBuilderUtils.jsx", "source_location": "L1"}, {"id": "querybuilderutils_uid", "label": "uid()", "file_type": "code", "source_file": "C:\\Users\\Vatsal\\Document\\VSCodeFiles\\PythonCode\\SmartDashBoardMaker\\frontend\\src\\lib\\queryBuilderUtils.jsx", "source_location": "L11"}, {"id": "querybuilderutils_quoteidentifier", "label": "quoteIdentifier()", "file_type": "code", "source_file": "C:\\Users\\Vatsal\\Document\\VSCodeFiles\\PythonCode\\SmartDashBoardMaker\\frontend\\src\\lib\\queryBuilderUtils.jsx", "source_location": "L13"}, {"id": "querybuilderutils_infertype", "label": "inferType()", "file_type": "code", "source_file": "C:\\Users\\Vatsal\\Document\\VSCodeFiles\\PythonCode\\SmartDashBoardMaker\\frontend\\src\\lib\\queryBuilderUtils.jsx", "source_location": "L35"}, {"id": "querybuilderutils_colpicker", "label": "ColPicker()", "file_type": "code", "source_file": "C:\\Users\\Vatsal\\Document\\VSCodeFiles\\PythonCode\\SmartDashBoardMaker\\frontend\\src\\lib\\queryBuilderUtils.jsx", "source_location": "L49"}, {"id": "querybuilderutils_sectionhdr", "label": "SectionHdr()", "file_type": "code", "source_file": "C:\\Users\\Vatsal\\Document\\VSCodeFiles\\PythonCode\\SmartDashBoardMaker\\frontend\\src\\lib\\queryBuilderUtils.jsx", "source_location": "L122"}, {"id": "querybuilderutils_colsel", "label": "ColSel()", "file_type": "code", "source_file": "C:\\Users\\Vatsal\\Document\\VSCodeFiles\\PythonCode\\SmartDashBoardMaker\\frontend\\src\\lib\\queryBuilderUtils.jsx", "source_location": "L144"}, {"id": "querybuilderutils_valinput", "label": "ValInput()", "file_type": "code", "source_file": "C:\\Users\\Vatsal\\Document\\VSCodeFiles\\PythonCode\\SmartDashBoardMaker\\frontend\\src\\lib\\queryBuilderUtils.jsx", "source_location": "L173"}, {"id": "querybuilderutils_extractctecols", "label": "extractCteCols()", "file_type": "code", "source_file": "C:\\Users\\Vatsal\\Document\\VSCodeFiles\\PythonCode\\SmartDashBoardMaker\\frontend\\src\\lib\\queryBuilderUtils.jsx", "source_location": "L236"}, {"id": "querybuilderutils_ctecolpicker", "label": "CteColPicker()", "file_type": "code", "source_file": "C:\\Users\\Vatsal\\Document\\VSCodeFiles\\PythonCode\\SmartDashBoardMaker\\frontend\\src\\lib\\queryBuilderUtils.jsx", "source_location": "L249"}, {"id": "querybuilderutils_derivecomputedcols", "label": "deriveComputedCols()", "file_type": "code", "source_file": "C:\\Users\\Vatsal\\Document\\VSCodeFiles\\PythonCode\\SmartDashBoardMaker\\frontend\\src\\lib\\queryBuilderUtils.jsx", "source_location": "L285"}, {"id": "querybuilderutils_buildsql", "label": "buildSQL()", "file_type": "code", "source_file": "C:\\Users\\Vatsal\\Document\\VSCodeFiles\\PythonCode\\SmartDashBoardMaker\\frontend\\src\\lib\\queryBuilderUtils.jsx", "source_location": "L294"}], "edges": [{"source": "c_users_vatsal_document_vscodefiles_pythoncode_smartdashboardmaker_frontend_src_lib_querybuilderutils_jsx", "target": "lucide_react", "relation": "imports_from", "confidence": "EXTRACTED", "source_file": "C:\\Users\\Vatsal\\Document\\VSCodeFiles\\PythonCode\\SmartDashBoardMaker\\frontend\\src\\lib\\queryBuilderUtils.jsx", "source_location": "L1", "weight": 1.0}, {"source": "c_users_vatsal_document_vscodefiles_pythoncode_smartdashboardmaker_frontend_src_lib_querybuilderutils_jsx", "target": "react", "relation": "imports_from", "confidence": "EXTRACTED", "source_file": "C:\\Users\\Vatsal\\Document\\VSCodeFiles\\PythonCode\\SmartDashBoardMaker\\frontend\\src\\lib\\queryBuilderUtils.jsx", "source_location": "L2", "weight": 1.0}, {"source": "c_users_vatsal_document_vscodefiles_pythoncode_smartdashboardmaker_frontend_src_lib_querybuilderutils_jsx", "target": "c_users_vatsal_document_vscodefiles_pythoncode_smartdashboardmaker_frontend_src_components_query_wherebuilder", "relation": "imports_from", "confidence": "EXTRACTED", "source_file": "C:\\Users\\Vatsal\\Document\\VSCodeFiles\\PythonCode\\SmartDashBoardMaker\\frontend\\src\\lib\\queryBuilderUtils.jsx", "source_location": "L4", "weight": 1.0}, {"source": "c_users_vatsal_document_vscodefiles_pythoncode_smartdashboardmaker_frontend_src_lib_querybuilderutils_jsx", "target": "c_users_vatsal_document_vscodefiles_pythoncode_smartdashboardmaker_frontend_src_components_query_havingbuilder", "relation": "imports_from", "confidence": "EXTRACTED", "source_file": "C:\\Users\\Vatsal\\Document\\VSCodeFiles\\PythonCode\\SmartDashBoardMaker\\frontend\\src\\lib\\queryBuilderUtils.jsx", "source_location": "L5", "weight": 1.0}, {"source": "c_users_vatsal_document_vscodefiles_pythoncode_smartdashboardmaker_frontend_src_lib_querybuilderutils_jsx", "target": "c_users_vatsal_document_vscodefiles_pythoncode_smartdashboardmaker_frontend_src_components_query_casebuilder", "relation": "imports_from", "confidence": "EXTRACTED", "source_file": "C:\\Users\\Vatsal\\Document\\VSCodeFiles\\PythonCode\\SmartDashBoardMaker\\frontend\\src\\lib\\queryBuilderUtils.jsx", "source_location": "L6", "weight": 1.0}, {"source": "c_users_vatsal_document_vscodefiles_pythoncode_smartdashboardmaker_frontend_src_lib_querybuilderutils_jsx", "target": "c_users_vatsal_document_vscodefiles_pythoncode_smartdashboardmaker_frontend_src_components_query_unionbuilder", "relation": "imports_from", "confidence": "EXTRACTED", "source_file": "C:\\Users\\Vatsal\\Document\\VSCodeFiles\\PythonCode\\SmartDashBoardMaker\\frontend\\src\\lib\\queryBuilderUtils.jsx", "source_location": "L7", "weight": 1.0}, {"source": "c_users_vatsal_document_vscodefiles_pythoncode_smartdashboardmaker_frontend_src_lib_querybuilderutils_jsx", "target": "c_users_vatsal_document_vscodefiles_pythoncode_smartdashboardmaker_frontend_src_components_query_nullfunctionsbuilder", "relation": "imports_from", "confidence": "EXTRACTED", "source_file": "C:\\Users\\Vatsal\\Document\\VSCodeFiles\\PythonCode\\SmartDashBoardMaker\\frontend\\src\\lib\\queryBuilderUtils.jsx", "source_location": "L8", "weight": 1.0}, {"source": "c_users_vatsal_document_vscodefiles_pythoncode_smartdashboardmaker_frontend_src_lib_querybuilderutils_jsx", "target": "querybuilderutils_uid", "relation": "contains", "confidence": "EXTRACTED", "source_file": "C:\\Users\\Vatsal\\Document\\VSCodeFiles\\PythonCode\\SmartDashBoardMaker\\frontend\\src\\lib\\queryBuilderUtils.jsx", "source_location": "L11", "weight": 1.0}, {"source": "c_users_vatsal_document_vscodefiles_pythoncode_smartdashboardmaker_frontend_src_lib_querybuilderutils_jsx", "target": "querybuilderutils_quoteidentifier", "relation": "contains", "confidence": "EXTRACTED", "source_file": "C:\\Users\\Vatsal\\Document\\VSCodeFiles\\PythonCode\\SmartDashBoardMaker\\frontend\\src\\lib\\queryBuilderUtils.jsx", "source_location": "L13", "weight": 1.0}, {"source": "c_users_vatsal_document_vscodefiles_pythoncode_smartdashboardmaker_frontend_src_lib_querybuilderutils_jsx", "target": "querybuilderutils_infertype", "relation": "contains", "confidence": "EXTRACTED", "source_file": "C:\\Users\\Vatsal\\Document\\VSCodeFiles\\PythonCode\\SmartDashBoardMaker\\frontend\\src\\lib\\queryBuilderUtils.jsx", "source_location": "L35", "weight": 1.0}, {"source": "c_users_vatsal_document_vscodefiles_pythoncode_smartdashboardmaker_frontend_src_lib_querybuilderutils_jsx", "target": "querybuilderutils_colpicker", "relation": "contains", "confidence": "EXTRACTED", "source_file": "C:\\Users\\Vatsal\\Document\\VSCodeFiles\\PythonCode\\SmartDashBoardMaker\\frontend\\src\\lib\\queryBuilderUtils.jsx", "source_location": "L49", "weight": 1.0}, {"source": "c_users_vatsal_document_vscodefiles_pythoncode_smartdashboardmaker_frontend_src_lib_querybuilderutils_jsx", "target": "querybuilderutils_sectionhdr", "relation": "contains", "confidence": "EXTRACTED", "source_file": "C:\\Users\\Vatsal\\Document\\VSCodeFiles\\PythonCode\\SmartDashBoardMaker\\frontend\\src\\lib\\queryBuilderUtils.jsx", "source_location": "L122", "weight": 1.0}, {"source": "c_users_vatsal_document_vscodefiles_pythoncode_smartdashboardmaker_frontend_src_lib_querybuilderutils_jsx", "target": "querybuilderutils_colsel", "relation": "contains", "confidence": "EXTRACTED", "source_file": "C:\\Users\\Vatsal\\Document\\VSCodeFiles\\PythonCode\\SmartDashBoardMaker\\frontend\\src\\lib\\queryBuilderUtils.jsx", "source_location": "L144", "weight": 1.0}, {"source": "c_users_vatsal_document_vscodefiles_pythoncode_smartdashboardmaker_frontend_src_lib_querybuilderutils_jsx", "target": "querybuilderutils_valinput", "relation": "contains", "confidence": "EXTRACTED", "source_file": "C:\\Users\\Vatsal\\Document\\VSCodeFiles\\PythonCode\\SmartDashBoardMaker\\frontend\\src\\lib\\queryBuilderUtils.jsx", "source_location": "L173", "weight": 1.0}, {"source": "c_users_vatsal_document_vscodefiles_pythoncode_smartdashboardmaker_frontend_src_lib_querybuilderutils_jsx", "target": "querybuilderutils_extractctecols", "relation": "contains", "confidence": "EXTRACTED", "source_file": "C:\\Users\\Vatsal\\Document\\VSCodeFiles\\PythonCode\\SmartDashBoardMaker\\frontend\\src\\lib\\queryBuilderUtils.jsx", "source_location": "L236", "weight": 1.0}, {"source": "c_users_vatsal_document_vscodefiles_pythoncode_smartdashboardmaker_frontend_src_lib_querybuilderutils_jsx", "target": "querybuilderutils_ctecolpicker", "relation": "contains", "confidence": "EXTRACTED", "source_file": "C:\\Users\\Vatsal\\Document\\VSCodeFiles\\PythonCode\\SmartDashBoardMaker\\frontend\\src\\lib\\queryBuilderUtils.jsx", "source_location": "L249", "weight": 1.0}, {"source": "c_users_vatsal_document_vscodefiles_pythoncode_smartdashboardmaker_frontend_src_lib_querybuilderutils_jsx", "target": "querybuilderutils_derivecomputedcols", "relation": "contains", "confidence": "EXTRACTED", "source_file": "C:\\Users\\Vatsal\\Document\\VSCodeFiles\\PythonCode\\SmartDashBoardMaker\\frontend\\src\\lib\\queryBuilderUtils.jsx", "source_location": "L285", "weight": 1.0}, {"source": "c_users_vatsal_document_vscodefiles_pythoncode_smartdashboardmaker_frontend_src_lib_querybuilderutils_jsx", "target": "querybuilderutils_buildsql", "relation": "contains", "confidence": "EXTRACTED", "source_file": "C:\\Users\\Vatsal\\Document\\VSCodeFiles\\PythonCode\\SmartDashBoardMaker\\frontend\\src\\lib\\queryBuilderUtils.jsx", "source_location": "L294", "weight": 1.0}, {"source": "querybuilderutils_colpicker", "target": "querybuilderutils_infertype", "relation": "calls", "confidence": "EXTRACTED", "source_file": "C:\\Users\\Vatsal\\Document\\VSCodeFiles\\PythonCode\\SmartDashBoardMaker\\frontend\\src\\lib\\queryBuilderUtils.jsx", "source_location": "L69", "weight": 1.0}, {"source": "querybuilderutils_ctecolpicker", "target": "querybuilderutils_extractctecols", "relation": "calls", "confidence": "EXTRACTED", "source_file": "C:\\Users\\Vatsal\\Document\\VSCodeFiles\\PythonCode\\SmartDashBoardMaker\\frontend\\src\\lib\\queryBuilderUtils.jsx", "source_location": "L254", "weight": 1.0}], "raw_calls": [{"caller_nid": "querybuilderutils_quoteidentifier", "callee": "String", "source_file": "C:\\Users\\Vatsal\\Document\\VSCodeFiles\\PythonCode\\SmartDashBoardMaker\\frontend\\src\\lib\\queryBuilderUtils.jsx", "source_location": "L16"}, {"caller_nid": "querybuilderutils_quoteidentifier", "callee": "includes", "source_file": "C:\\Users\\Vatsal\\Document\\VSCodeFiles\\PythonCode\\SmartDashBoardMaker\\frontend\\src\\lib\\queryBuilderUtils.jsx", "source_location": "L17"}, {"caller_nid": "querybuilderutils_quoteidentifier", "callee": "includes", "source_file": "C:\\Users\\Vatsal\\Document\\VSCodeFiles\\PythonCode\\SmartDashBoardMaker\\frontend\\src\\lib\\queryBuilderUtils.jsx", "source_location": "L20"}, {"caller_nid": "querybuilderutils_quoteidentifier", "callee": "join", "source_file": "C:\\Users\\Vatsal\\Document\\VSCodeFiles\\PythonCode\\SmartDashBoardMaker\\frontend\\src\\lib\\queryBuilderUtils.jsx", "source_location": "L21"}, {"caller_nid": "querybuilderutils_quoteidentifier", "callee": "map", "source_file": "C:\\Users\\Vatsal\\Document\\VSCodeFiles\\PythonCode\\SmartDashBoardMaker\\frontend\\src\\lib\\queryBuilderUtils.jsx", "source_location": "L21"}, {"caller_nid": "querybuilderutils_quoteidentifier", "callee": "split", "source_file": "C:\\Users\\Vatsal\\Document\\VSCodeFiles\\PythonCode\\SmartDashBoardMaker\\frontend\\src\\lib\\queryBuilderUtils.jsx", "source_location": "L21"}, {"caller_nid": "querybuilderutils_quoteidentifier", "callee": "has", "source_file": "C:\\Users\\Vatsal\\Document\\VSCodeFiles\\PythonCode\\SmartDashBoardMaker\\frontend\\src\\lib\\queryBuilderUtils.jsx", "source_location": "L23"}, {"caller_nid": "querybuilderutils_quoteidentifier", "callee": "toLowerCase", "source_file": "C:\\Users\\Vatsal\\Document\\VSCodeFiles\\PythonCode\\SmartDashBoardMaker\\frontend\\src\\lib\\queryBuilderUtils.jsx", "source_location": "L23"}, {"caller_nid": "querybuilderutils_infertype", "callee": "toLowerCase", "source_file": "C:\\Users\\Vatsal\\Document\\VSCodeFiles\\PythonCode\\SmartDashBoardMaker\\frontend\\src\\lib\\queryBuilderUtils.jsx", "source_location": "L36"}, {"caller_nid": "querybuilderutils_infertype", "callee": "test", "source_file": "C:\\Users\\Vatsal\\Document\\VSCodeFiles\\PythonCode\\SmartDashBoardMaker\\frontend\\src\\lib\\queryBuilderUtils.jsx", "source_location": "L37"}, {"caller_nid": "querybuilderutils_infertype", "callee": "test", "source_file": "C:\\Users\\Vatsal\\Document\\VSCodeFiles\\PythonCode\\SmartDashBoardMaker\\frontend\\src\\lib\\queryBuilderUtils.jsx", "source_location": "L38"}, {"caller_nid": "querybuilderutils_infertype", "callee": "test", "source_file": "C:\\Users\\Vatsal\\Document\\VSCodeFiles\\PythonCode\\SmartDashBoardMaker\\frontend\\src\\lib\\queryBuilderUtils.jsx", "source_location": "L39"}, {"caller_nid": "querybuilderutils_colpicker", "callee": "useState", "source_file": "C:\\Users\\Vatsal\\Document\\VSCodeFiles\\PythonCode\\SmartDashBoardMaker\\frontend\\src\\lib\\queryBuilderUtils.jsx", "source_location": "L50"}, {"caller_nid": "querybuilderutils_colpicker", "callee": "useState", "source_file": "C:\\Users\\Vatsal\\Document\\VSCodeFiles\\PythonCode\\SmartDashBoardMaker\\frontend\\src\\lib\\queryBuilderUtils.jsx", "source_location": "L51"}, {"caller_nid": "querybuilderutils_colpicker", "callee": "useRef", "source_file": "C:\\Users\\Vatsal\\Document\\VSCodeFiles\\PythonCode\\SmartDashBoardMaker\\frontend\\src\\lib\\queryBuilderUtils.jsx", "source_location": "L52"}, {"caller_nid": "querybuilderutils_colpicker", "callee": "useEffect", "source_file": "C:\\Users\\Vatsal\\Document\\VSCodeFiles\\PythonCode\\SmartDashBoardMaker\\frontend\\src\\lib\\queryBuilderUtils.jsx", "source_location": "L54"}, {"caller_nid": "querybuilderutils_colpicker", "callee": "useMemo", "source_file": "C:\\Users\\Vatsal\\Document\\VSCodeFiles\\PythonCode\\SmartDashBoardMaker\\frontend\\src\\lib\\queryBuilderUtils.jsx", "source_location": "L62"}, {"caller_nid": "querybuilderutils_colpicker", "callee": "colMeta", "source_file": "C:\\Users\\Vatsal\\Document\\VSCodeFiles\\PythonCode\\SmartDashBoardMaker\\frontend\\src\\lib\\queryBuilderUtils.jsx", "source_location": "L68"}, {"caller_nid": "querybuilderutils_colpicker", "callee": "map", "source_file": "C:\\Users\\Vatsal\\Document\\VSCodeFiles\\PythonCode\\SmartDashBoardMaker\\frontend\\src\\lib\\queryBuilderUtils.jsx", "source_location": "L91"}, {"caller_nid": "querybuilderutils_colpicker", "callee": "map", "source_file": "C:\\Users\\Vatsal\\Document\\VSCodeFiles\\PythonCode\\SmartDashBoardMaker\\frontend\\src\\lib\\queryBuilderUtils.jsx", "source_location": "L104"}, {"caller_nid": "querybuilderutils_colsel", "callee": "map", "source_file": "C:\\Users\\Vatsal\\Document\\VSCodeFiles\\PythonCode\\SmartDashBoardMaker\\frontend\\src\\lib\\queryBuilderUtils.jsx", "source_location": "L154"}, {"caller_nid": "querybuilderutils_colsel", "callee": "map", "source_file": "C:\\Users\\Vatsal\\Document\\VSCodeFiles\\PythonCode\\SmartDashBoardMaker\\frontend\\src\\lib\\queryBuilderUtils.jsx", "source_location": "L160"}, {"caller_nid": "querybuilderutils_colsel", "callee": "map", "source_file": "C:\\Users\\Vatsal\\Document\\VSCodeFiles\\PythonCode\\SmartDashBoardMaker\\frontend\\src\\lib\\queryBuilderUtils.jsx", "source_location": "L163"}, {"caller_nid": "querybuilderutils_colsel", "callee": "map", "source_file": "C:\\Users\\Vatsal\\Document\\VSCodeFiles\\PythonCode\\SmartDashBoardMaker\\frontend\\src\\lib\\queryBuilderUtils.jsx", "source_location": "L167"}, {"caller_nid": "querybuilderutils_valinput", "callee": "useState", "source_file": "C:\\Users\\Vatsal\\Document\\VSCodeFiles\\PythonCode\\SmartDashBoardMaker\\frontend\\src\\lib\\queryBuilderUtils.jsx", "source_location": "L174"}, {"caller_nid": "querybuilderutils_valinput", "callee": "useState", "source_file": "C:\\Users\\Vatsal\\Document\\VSCodeFiles\\PythonCode\\SmartDashBoardMaker\\frontend\\src\\lib\\queryBuilderUtils.jsx", "source_location": "L175"}, {"caller_nid": "querybuilderutils_valinput", "callee": "useRef", "source_file": "C:\\Users\\Vatsal\\Document\\VSCodeFiles\\PythonCode\\SmartDashBoardMaker\\frontend\\src\\lib\\queryBuilderUtils.jsx", "source_location": "L176"}, {"caller_nid": "querybuilderutils_valinput", "callee": "isArray", "source_file": "C:\\Users\\Vatsal\\Document\\VSCodeFiles\\PythonCode\\SmartDashBoardMaker\\frontend\\src\\lib\\queryBuilderUtils.jsx", "source_location": "L180"}, {"caller_nid": "querybuilderutils_valinput", "callee": "filter", "source_file": "C:\\Users\\Vatsal\\Document\\VSCodeFiles\\PythonCode\\SmartDashBoardMaker\\frontend\\src\\lib\\queryBuilderUtils.jsx", "source_location": "L180"}, {"caller_nid": "querybuilderutils_valinput", "callee": "map", "source_file": "C:\\Users\\Vatsal\\Document\\VSCodeFiles\\PythonCode\\SmartDashBoardMaker\\frontend\\src\\lib\\queryBuilderUtils.jsx", "source_location": "L180"}, {"caller_nid": "querybuilderutils_valinput", "callee": "split", "source_file": "C:\\Users\\Vatsal\\Document\\VSCodeFiles\\PythonCode\\SmartDashBoardMaker\\frontend\\src\\lib\\queryBuilderUtils.jsx", "source_location": "L180"}, {"caller_nid": "querybuilderutils_valinput", "callee": "String", "source_file": "C:\\Users\\Vatsal\\Document\\VSCodeFiles\\PythonCode\\SmartDashBoardMaker\\frontend\\src\\lib\\queryBuilderUtils.jsx", "source_location": "L180"}, {"caller_nid": "querybuilderutils_valinput", "callee": "filter", "source_file": "C:\\Users\\Vatsal\\Document\\VSCodeFiles\\PythonCode\\SmartDashBoardMaker\\frontend\\src\\lib\\queryBuilderUtils.jsx", "source_location": "L181"}, {"caller_nid": "querybuilderutils_valinput", "callee": "useEffect", "source_file": "C:\\Users\\Vatsal\\Document\\VSCodeFiles\\PythonCode\\SmartDashBoardMaker\\frontend\\src\\lib\\queryBuilderUtils.jsx", "source_location": "L183"}, {"caller_nid": "querybuilderutils_valinput", "callee": "isArray", "source_file": "C:\\Users\\Vatsal\\Document\\VSCodeFiles\\PythonCode\\SmartDashBoardMaker\\frontend\\src\\lib\\queryBuilderUtils.jsx", "source_location": "L191"}, {"caller_nid": "querybuilderutils_valinput", "callee": "split", "source_file": "C:\\Users\\Vatsal\\Document\\VSCodeFiles\\PythonCode\\SmartDashBoardMaker\\frontend\\src\\lib\\queryBuilderUtils.jsx", "source_location": "L191"}, {"caller_nid": "querybuilderutils_valinput", "callee": "map", "source_file": "C:\\Users\\Vatsal\\Document\\VSCodeFiles\\PythonCode\\SmartDashBoardMaker\\frontend\\src\\lib\\queryBuilderUtils.jsx", "source_location": "L206"}, {"caller_nid": "querybuilderutils_valinput", "callee": "isArray", "source_file": "C:\\Users\\Vatsal\\Document\\VSCodeFiles\\PythonCode\\SmartDashBoardMaker\\frontend\\src\\lib\\queryBuilderUtils.jsx", "source_location": "L214"}, {"caller_nid": "querybuilderutils_valinput", "callee": "map", "source_file": "C:\\Users\\Vatsal\\Document\\VSCodeFiles\\PythonCode\\SmartDashBoardMaker\\frontend\\src\\lib\\queryBuilderUtils.jsx", "source_location": "L223"}, {"caller_nid": "querybuilderutils_valinput", "callee": "slice", "source_file": "C:\\Users\\Vatsal\\Document\\VSCodeFiles\\PythonCode\\SmartDashBoardMaker\\frontend\\src\\lib\\queryBuilderUtils.jsx", "source_location": "L223"}, {"caller_nid": "querybuilderutils_extractctecols", "callee": "matchAll", "source_file": "C:\\Users\\Vatsal\\Document\\VSCodeFiles\\PythonCode\\SmartDashBoardMaker\\frontend\\src\\lib\\queryBuilderUtils.jsx", "source_location": "L238"}, {"caller_nid": "querybuilderutils_extractctecols", "callee": "map", "source_file": "C:\\Users\\Vatsal\\Document\\VSCodeFiles\\PythonCode\\SmartDashBoardMaker\\frontend\\src\\lib\\queryBuilderUtils.jsx", "source_location": "L239"}, {"caller_nid": "querybuilderutils_extractctecols", "callee": "match", "source_file": "C:\\Users\\Vatsal\\Document\\VSCodeFiles\\PythonCode\\SmartDashBoardMaker\\frontend\\src\\lib\\queryBuilderUtils.jsx", "source_location": "L240"}, {"caller_nid": "querybuilderutils_extractctecols", "callee": "map", "source_file": "C:\\Users\\Vatsal\\Document\\VSCodeFiles\\PythonCode\\SmartDashBoardMaker\\frontend\\src\\lib\\queryBuilderUtils.jsx", "source_location": "L243"}, {"caller_nid": "querybuilderutils_extractctecols", "callee": "split", "source_file": "C:\\Users\\Vatsal\\Document\\VSCodeFiles\\PythonCode\\SmartDashBoardMaker\\frontend\\src\\lib\\queryBuilderUtils.jsx", "source_location": "L243"}, {"caller_nid": "querybuilderutils_extractctecols", "callee": "forEach", "source_file": "C:\\Users\\Vatsal\\Document\\VSCodeFiles\\PythonCode\\SmartDashBoardMaker\\frontend\\src\\lib\\queryBuilderUtils.jsx", "source_location": "L244"}, {"caller_nid": "querybuilderutils_ctecolpicker", "callee": "useState", "source_file": "C:\\Users\\Vatsal\\Document\\VSCodeFiles\\PythonCode\\SmartDashBoardMaker\\frontend\\src\\lib\\queryBuilderUtils.jsx", "source_location": "L250"}, {"caller_nid": "querybuilderutils_ctecolpicker", "callee": "useState", "source_file": "C:\\Users\\Vatsal\\Document\\VSCodeFiles\\PythonCode\\SmartDashBoardMaker\\frontend\\src\\lib\\queryBuilderUtils.jsx", "source_location": "L251"}, {"caller_nid": "querybuilderutils_ctecolpicker", "callee": "useRef", "source_file": "C:\\Users\\Vatsal\\Document\\VSCodeFiles\\PythonCode\\SmartDashBoardMaker\\frontend\\src\\lib\\queryBuilderUtils.jsx", "source_location": "L252"}, {"caller_nid": "querybuilderutils_ctecolpicker", "callee": "filter", "source_file": "C:\\Users\\Vatsal\\Document\\VSCodeFiles\\PythonCode\\SmartDashBoardMaker\\frontend\\src\\lib\\queryBuilderUtils.jsx", "source_location": "L255"}, {"caller_nid": "querybuilderutils_ctecolpicker", "callee": "useEffect", "source_file": "C:\\Users\\Vatsal\\Document\\VSCodeFiles\\PythonCode\\SmartDashBoardMaker\\frontend\\src\\lib\\queryBuilderUtils.jsx", "source_location": "L257"}, {"caller_nid": "querybuilderutils_ctecolpicker", "callee": "map", "source_file": "C:\\Users\\Vatsal\\Document\\VSCodeFiles\\PythonCode\\SmartDashBoardMaker\\frontend\\src\\lib\\queryBuilderUtils.jsx", "source_location": "L274"}, {"caller_nid": "querybuilderutils_derivecomputedcols", "callee": "forEach", "source_file": "C:\\Users\\Vatsal\\Document\\VSCodeFiles\\PythonCode\\SmartDashBoardMaker\\frontend\\src\\lib\\queryBuilderUtils.jsx", "source_location": "L287"}, {"caller_nid": "querybuilderutils_derivecomputedcols", "callee": "forEach", "source_file": "C:\\Users\\Vatsal\\Document\\VSCodeFiles\\PythonCode\\SmartDashBoardMaker\\frontend\\src\\lib\\queryBuilderUtils.jsx", "source_location": "L288"}, {"caller_nid": "querybuilderutils_derivecomputedcols", "callee": "forEach", "source_file": "C:\\Users\\Vatsal\\Document\\VSCodeFiles\\PythonCode\\SmartDashBoardMaker\\frontend\\src\\lib\\queryBuilderUtils.jsx", "source_location": "L289"}, {"caller_nid": "querybuilderutils_derivecomputedcols", "callee": "forEach", "source_file": "C:\\Users\\Vatsal\\Document\\VSCodeFiles\\PythonCode\\SmartDashBoardMaker\\frontend\\src\\lib\\queryBuilderUtils.jsx", "source_location": "L290"}, {"caller_nid": "querybuilderutils_buildsql", "callee": "filter", "source_file": "C:\\Users\\Vatsal\\Document\\VSCodeFiles\\PythonCode\\SmartDashBoardMaker\\frontend\\src\\lib\\queryBuilderUtils.jsx", "source_location": "L301"}, {"caller_nid": "querybuilderutils_buildsql", "callee": "push", "source_file": "C:\\Users\\Vatsal\\Document\\VSCodeFiles\\PythonCode\\SmartDashBoardMaker\\frontend\\src\\lib\\queryBuilderUtils.jsx", "source_location": "L303"}, {"caller_nid": "querybuilderutils_buildsql", "callee": "join", "source_file": "C:\\Users\\Vatsal\\Document\\VSCodeFiles\\PythonCode\\SmartDashBoardMaker\\frontend\\src\\lib\\queryBuilderUtils.jsx", "source_location": "L303"}, {"caller_nid": "querybuilderutils_buildsql", "callee": "map", "source_file": "C:\\Users\\Vatsal\\Document\\VSCodeFiles\\PythonCode\\SmartDashBoardMaker\\frontend\\src\\lib\\queryBuilderUtils.jsx", "source_location": "L303"}, {"caller_nid": "querybuilderutils_buildsql", "callee": "buildUnionSQL", "source_file": "C:\\Users\\Vatsal\\Document\\VSCodeFiles\\PythonCode\\SmartDashBoardMaker\\frontend\\src\\lib\\queryBuilderUtils.jsx", "source_location": "L306"}, {"caller_nid": "querybuilderutils_buildsql", "callee": "push", "source_file": "C:\\Users\\Vatsal\\Document\\VSCodeFiles\\PythonCode\\SmartDashBoardMaker\\frontend\\src\\lib\\queryBuilderUtils.jsx", "source_location": "L307"}, {"caller_nid": "querybuilderutils_buildsql", "callee": "push", "source_file": "C:\\Users\\Vatsal\\Document\\VSCodeFiles\\PythonCode\\SmartDashBoardMaker\\frontend\\src\\lib\\queryBuilderUtils.jsx", "source_location": "L308"}, {"caller_nid": "querybuilderutils_buildsql", "callee": "push", "source_file": "C:\\Users\\Vatsal\\Document\\VSCodeFiles\\PythonCode\\SmartDashBoardMaker\\frontend\\src\\lib\\queryBuilderUtils.jsx", "source_location": "L309"}, {"caller_nid": "querybuilderutils_buildsql", "callee": "join", "source_file": "C:\\Users\\Vatsal\\Document\\VSCodeFiles\\PythonCode\\SmartDashBoardMaker\\frontend\\src\\lib\\queryBuilderUtils.jsx", "source_location": "L310"}, {"caller_nid": "querybuilderutils_buildsql", "callee": "track", "source_file": "C:\\Users\\Vatsal\\Document\\VSCodeFiles\\PythonCode\\SmartDashBoardMaker\\frontend\\src\\lib\\queryBuilderUtils.jsx", "source_location": "L319"}, {"caller_nid": "querybuilderutils_buildsql", "callee": "forEach", "source_file": "C:\\Users\\Vatsal\\Document\\VSCodeFiles\\PythonCode\\SmartDashBoardMaker\\frontend\\src\\lib\\queryBuilderUtils.jsx", "source_location": "L320"}, {"caller_nid": "querybuilderutils_buildsql", "callee": "filter", "source_file": "C:\\Users\\Vatsal\\Document\\VSCodeFiles\\PythonCode\\SmartDashBoardMaker\\frontend\\src\\lib\\queryBuilderUtils.jsx", "source_location": "L322"}, {"caller_nid": "querybuilderutils_buildsql", "callee": "keys", "source_file": "C:\\Users\\Vatsal\\Document\\VSCodeFiles\\PythonCode\\SmartDashBoardMaker\\frontend\\src\\lib\\queryBuilderUtils.jsx", "source_location": "L322"}, {"caller_nid": "querybuilderutils_buildsql", "callee": "startsWith", "source_file": "C:\\Users\\Vatsal\\Document\\VSCodeFiles\\PythonCode\\SmartDashBoardMaker\\frontend\\src\\lib\\queryBuilderUtils.jsx", "source_location": "L325"}, {"caller_nid": "querybuilderutils_buildsql", "callee": "find", "source_file": "C:\\Users\\Vatsal\\Document\\VSCodeFiles\\PythonCode\\SmartDashBoardMaker\\frontend\\src\\lib\\queryBuilderUtils.jsx", "source_location": "L326"}, {"caller_nid": "querybuilderutils_buildsql", "callee": "replace", "source_file": "C:\\Users\\Vatsal\\Document\\VSCodeFiles\\PythonCode\\SmartDashBoardMaker\\frontend\\src\\lib\\queryBuilderUtils.jsx", "source_location": "L328"}, {"caller_nid": "querybuilderutils_buildsql", "callee": "filter", "source_file": "C:\\Users\\Vatsal\\Document\\VSCodeFiles\\PythonCode\\SmartDashBoardMaker\\frontend\\src\\lib\\queryBuilderUtils.jsx", "source_location": "L332"}, {"caller_nid": "querybuilderutils_buildsql", "callee": "map", "source_file": "C:\\Users\\Vatsal\\Document\\VSCodeFiles\\PythonCode\\SmartDashBoardMaker\\frontend\\src\\lib\\queryBuilderUtils.jsx", "source_location": "L333"}, {"caller_nid": "querybuilderutils_buildsql", "callee": "filter", "source_file": "C:\\Users\\Vatsal\\Document\\VSCodeFiles\\PythonCode\\SmartDashBoardMaker\\frontend\\src\\lib\\queryBuilderUtils.jsx", "source_location": "L333"}, {"caller_nid": "querybuilderutils_buildsql", "callee": "filter", "source_file": "C:\\Users\\Vatsal\\Document\\VSCodeFiles\\PythonCode\\SmartDashBoardMaker\\frontend\\src\\lib\\queryBuilderUtils.jsx", "source_location": "L334"}, {"caller_nid": "querybuilderutils_buildsql", "callee": "map", "source_file": "C:\\Users\\Vatsal\\Document\\VSCodeFiles\\PythonCode\\SmartDashBoardMaker\\frontend\\src\\lib\\queryBuilderUtils.jsx", "source_location": "L335"}, {"caller_nid": "querybuilderutils_buildsql", "callee": "map", "source_file": "C:\\Users\\Vatsal\\Document\\VSCodeFiles\\PythonCode\\SmartDashBoardMaker\\frontend\\src\\lib\\queryBuilderUtils.jsx", "source_location": "L336"}, {"caller_nid": "querybuilderutils_buildsql", "callee": "map", "source_file": "C:\\Users\\Vatsal\\Document\\VSCodeFiles\\PythonCode\\SmartDashBoardMaker\\frontend\\src\\lib\\queryBuilderUtils.jsx", "source_location": "L337"}, {"caller_nid": "querybuilderutils_buildsql", "callee": "map", "source_file": "C:\\Users\\Vatsal\\Document\\VSCodeFiles\\PythonCode\\SmartDashBoardMaker\\frontend\\src\\lib\\queryBuilderUtils.jsx", "source_location": "L338"}, {"caller_nid": "querybuilderutils_buildsql", "callee": "forEach", "source_file": "C:\\Users\\Vatsal\\Document\\VSCodeFiles\\PythonCode\\SmartDashBoardMaker\\frontend\\src\\lib\\queryBuilderUtils.jsx", "source_location": "L342"}, {"caller_nid": "querybuilderutils_buildsql", "callee": "forEach", "source_file": "C:\\Users\\Vatsal\\Document\\VSCodeFiles\\PythonCode\\SmartDashBoardMaker\\frontend\\src\\lib\\queryBuilderUtils.jsx", "source_location": "L344"}, {"caller_nid": "querybuilderutils_buildsql", "callee": "forEach", "source_file": "C:\\Users\\Vatsal\\Document\\VSCodeFiles\\PythonCode\\SmartDashBoardMaker\\frontend\\src\\lib\\queryBuilderUtils.jsx", "source_location": "L352"}, {"caller_nid": "querybuilderutils_buildsql", "callee": "forEach", "source_file": "C:\\Users\\Vatsal\\Document\\VSCodeFiles\\PythonCode\\SmartDashBoardMaker\\frontend\\src\\lib\\queryBuilderUtils.jsx", "source_location": "L357"}, {"caller_nid": "querybuilderutils_buildsql", "callee": "forEach", "source_file": "C:\\Users\\Vatsal\\Document\\VSCodeFiles\\PythonCode\\SmartDashBoardMaker\\frontend\\src\\lib\\queryBuilderUtils.jsx", "source_location": "L362"}, {"caller_nid": "querybuilderutils_buildsql", "callee": "push", "source_file": "C:\\Users\\Vatsal\\Document\\VSCodeFiles\\PythonCode\\SmartDashBoardMaker\\frontend\\src\\lib\\queryBuilderUtils.jsx", "source_location": "L371"}, {"caller_nid": "querybuilderutils_buildsql", "callee": "push", "source_file": "C:\\Users\\Vatsal\\Document\\VSCodeFiles\\PythonCode\\SmartDashBoardMaker\\frontend\\src\\lib\\queryBuilderUtils.jsx", "source_location": "L372"}, {"caller_nid": "querybuilderutils_buildsql", "callee": "join", "source_file": "C:\\Users\\Vatsal\\Document\\VSCodeFiles\\PythonCode\\SmartDashBoardMaker\\frontend\\src\\lib\\queryBuilderUtils.jsx", "source_location": "L372"}, {"caller_nid": "querybuilderutils_buildsql", "callee": "push", "source_file": "C:\\Users\\Vatsal\\Document\\VSCodeFiles\\PythonCode\\SmartDashBoardMaker\\frontend\\src\\lib\\queryBuilderUtils.jsx", "source_location": "L374"}, {"caller_nid": "querybuilderutils_buildsql", "callee": "push", "source_file": "C:\\Users\\Vatsal\\Document\\VSCodeFiles\\PythonCode\\SmartDashBoardMaker\\frontend\\src\\lib\\queryBuilderUtils.jsx", "source_location": "L375"}, {"caller_nid": "querybuilderutils_buildsql", "callee": "forEach", "source_file": "C:\\Users\\Vatsal\\Document\\VSCodeFiles\\PythonCode\\SmartDashBoardMaker\\frontend\\src\\lib\\queryBuilderUtils.jsx", "source_location": "L377"}, {"caller_nid": "querybuilderutils_buildsql", "callee": "buildWhereSQL", "source_file": "C:\\Users\\Vatsal\\Document\\VSCodeFiles\\PythonCode\\SmartDashBoardMaker\\frontend\\src\\lib\\queryBuilderUtils.jsx", "source_location": "L403"}, {"caller_nid": "querybuilderutils_buildsql", "callee": "map", "source_file": "C:\\Users\\Vatsal\\Document\\VSCodeFiles\\PythonCode\\SmartDashBoardMaker\\frontend\\src\\lib\\queryBuilderUtils.jsx", "source_location": "L403"}, {"caller_nid": "querybuilderutils_buildsql", "callee": "push", "source_file": "C:\\Users\\Vatsal\\Document\\VSCodeFiles\\PythonCode\\SmartDashBoardMaker\\frontend\\src\\lib\\queryBuilderUtils.jsx", "source_location": "L404"}, {"caller_nid": "querybuilderutils_buildsql", "callee": "map", "source_file": "C:\\Users\\Vatsal\\Document\\VSCodeFiles\\PythonCode\\SmartDashBoardMaker\\frontend\\src\\lib\\queryBuilderUtils.jsx", "source_location": "L407"}, {"caller_nid": "querybuilderutils_buildsql", "callee": "push", "source_file": "C:\\Users\\Vatsal\\Document\\VSCodeFiles\\PythonCode\\SmartDashBoardMaker\\frontend\\src\\lib\\queryBuilderUtils.jsx", "source_location": "L412"}, {"caller_nid": "querybuilderutils_buildsql", "callee": "join", "source_file": "C:\\Users\\Vatsal\\Document\\VSCodeFiles\\PythonCode\\SmartDashBoardMaker\\frontend\\src\\lib\\queryBuilderUtils.jsx", "source_location": "L412"}, {"caller_nid": "querybuilderutils_buildsql", "callee": "buildHavingSQL", "source_file": "C:\\Users\\Vatsal\\Document\\VSCodeFiles\\PythonCode\\SmartDashBoardMaker\\frontend\\src\\lib\\queryBuilderUtils.jsx", "source_location": "L415"}, {"caller_nid": "querybuilderutils_buildsql", "callee": "map", "source_file": "C:\\Users\\Vatsal\\Document\\VSCodeFiles\\PythonCode\\SmartDashBoardMaker\\frontend\\src\\lib\\queryBuilderUtils.jsx", "source_location": "L415"}, {"caller_nid": "querybuilderutils_buildsql", "callee": "push", "source_file": "C:\\Users\\Vatsal\\Document\\VSCodeFiles\\PythonCode\\SmartDashBoardMaker\\frontend\\src\\lib\\queryBuilderUtils.jsx", "source_location": "L416"}, {"caller_nid": "querybuilderutils_buildsql", "callee": "filter", "source_file": "C:\\Users\\Vatsal\\Document\\VSCodeFiles\\PythonCode\\SmartDashBoardMaker\\frontend\\src\\lib\\queryBuilderUtils.jsx", "source_location": "L418"}, {"caller_nid": "querybuilderutils_buildsql", "callee": "map", "source_file": "C:\\Users\\Vatsal\\Document\\VSCodeFiles\\PythonCode\\SmartDashBoardMaker\\frontend\\src\\lib\\queryBuilderUtils.jsx", "source_location": "L420"}, {"caller_nid": "querybuilderutils_buildsql", "callee": "push", "source_file": "C:\\Users\\Vatsal\\Document\\VSCodeFiles\\PythonCode\\SmartDashBoardMaker\\frontend\\src\\lib\\queryBuilderUtils.jsx", "source_location": "L427"}, {"caller_nid": "querybuilderutils_buildsql", "callee": "join", "source_file": "C:\\Users\\Vatsal\\Document\\VSCodeFiles\\PythonCode\\SmartDashBoardMaker\\frontend\\src\\lib\\queryBuilderUtils.jsx", "source_location": "L427"}, {"caller_nid": "querybuilderutils_buildsql", "callee": "buildUnionSQL", "source_file": "C:\\Users\\Vatsal\\Document\\VSCodeFiles\\PythonCode\\SmartDashBoardMaker\\frontend\\src\\lib\\queryBuilderUtils.jsx", "source_location": "L431"}, {"caller_nid": "querybuilderutils_buildsql", "callee": "join", "source_file": "C:\\Users\\Vatsal\\Document\\VSCodeFiles\\PythonCode\\SmartDashBoardMaker\\frontend\\src\\lib\\queryBuilderUtils.jsx", "source_location": "L431"}, {"caller_nid": "querybuilderutils_buildsql", "callee": "push", "source_file": "C:\\Users\\Vatsal\\Document\\VSCodeFiles\\PythonCode\\SmartDashBoardMaker\\frontend\\src\\lib\\queryBuilderUtils.jsx", "source_location": "L432"}, {"caller_nid": "querybuilderutils_buildsql", "callee": "trim", "source_file": "C:\\Users\\Vatsal\\Document\\VSCodeFiles\\PythonCode\\SmartDashBoardMaker\\frontend\\src\\lib\\queryBuilderUtils.jsx", "source_location": "L435"}, {"caller_nid": "querybuilderutils_buildsql", "callee": "String", "source_file": "C:\\Users\\Vatsal\\Document\\VSCodeFiles\\PythonCode\\SmartDashBoardMaker\\frontend\\src\\lib\\queryBuilderUtils.jsx", "source_location": "L435"}, {"caller_nid": "querybuilderutils_buildsql", "callee": "push", "source_file": "C:\\Users\\Vatsal\\Document\\VSCodeFiles\\PythonCode\\SmartDashBoardMaker\\frontend\\src\\lib\\queryBuilderUtils.jsx", "source_location": "L435"}, {"caller_nid": "querybuilderutils_buildsql", "callee": "trim", "source_file": "C:\\Users\\Vatsal\\Document\\VSCodeFiles\\PythonCode\\SmartDashBoardMaker\\frontend\\src\\lib\\queryBuilderUtils.jsx", "source_location": "L436"}, {"caller_nid": "querybuilderutils_buildsql", "callee": "String", "source_file": "C:\\Users\\Vatsal\\Document\\VSCodeFiles\\PythonCode\\SmartDashBoardMaker\\frontend\\src\\lib\\queryBuilderUtils.jsx", "source_location": "L436"}, {"caller_nid": "querybuilderutils_buildsql", "callee": "push", "source_file": "C:\\Users\\Vatsal\\Document\\VSCodeFiles\\PythonCode\\SmartDashBoardMaker\\frontend\\src\\lib\\queryBuilderUtils.jsx", "source_location": "L436"}, {"caller_nid": "querybuilderutils_buildsql", "callee": "join", "source_file": "C:\\Users\\Vatsal\\Document\\VSCodeFiles\\PythonCode\\SmartDashBoardMaker\\frontend\\src\\lib\\queryBuilderUtils.jsx", "source_location": "L438"}]}